kohi/__init__.py
kohi/base.py
kohi/dictionary.py
kohi/enum.py
kohi/exceptions.py
kohi/number.py
kohi/string.py
kohi-0.4.0.dist-info/LICENSE
kohi-0.4.0.dist-info/WHEEL
kohi-0.4.0.dist-info/METADATA
kohi-0.4.0.dist-info/RECORD
