Metadata-Version: 2.1
Name: kohi
Version: 0.4.0
Summary: A powerfull schema validator
Home-page: https://github.com/natanfeitosa/kohi#readme
Keywords: data,validator,schema,json,science
Author: Natan Santos
Author-email: natansantosapps@gmail.com
Requires-Python: >=3.8,<4.0
Classifier: Development Status :: 3 - Alpha
Classifier: Intended Audience :: Developers
Classifier: License :: OSI Approved :: MIT License
Classifier: Programming Language :: Python
Classifier: Programming Language :: Python :: 3
Classifier: Programming Language :: Python :: 3.10
Classifier: Programming Language :: Python :: 3.8
Classifier: Programming Language :: Python :: 3.9
Classifier: Topic :: Software Development :: Libraries
Classifier: Topic :: Software Development :: Libraries :: Python Modules
Classifier: Topic :: Software Development :: Testing
Classifier: Typing :: Typed
Requires-Dist: pytest (>=7.2.2,<8.0.0)
Project-URL: Bug Tracker, https://github.com/natanfeitosa/kohi/issues
Project-URL: Repository, https://github.com/natanfeitosa/kohi
